COPYING
MANIFEST.in
README
setup.py
./__init__.py
./health_pediatrics_growth_charts.py
./tryton.cfg
./doc/index.rst
./locale/ar.po
./locale/de.po
./locale/el.po
./locale/es.po
./locale/fr.po
./locale/it_IT.po
./locale/ja_JP.po
./locale/lo.po
./locale/pt_BR.po
./locale/zh_CN.po
./tests/__init__.py
./tests/test_health_pediatrics_growth_charts.py
locale/ar.po
locale/de.po
locale/el.po
locale/es.po
locale/fr.po
locale/it_IT.po
locale/ja_JP.po
locale/lo.po
locale/pt_BR.po
locale/zh_CN.po
trytond_health_pediatrics_growth_charts.egg-info/PKG-INFO
trytond_health_pediatrics_growth_charts.egg-info/SOURCES.txt
trytond_health_pediatrics_growth_charts.egg-info/dependency_links.txt
trytond_health_pediatrics_growth_charts.egg-info/entry_points.txt
trytond_health_pediatrics_growth_charts.egg-info/not-zip-safe
trytond_health_pediatrics_growth_charts.egg-info/requires.txt
trytond_health_pediatrics_growth_charts.egg-info/top_level.txt